nonebot_plugin_qqdetail/__init__.py
nonebot_plugin_qqdetail/config.py
nonebot_plugin_qqdetail/draw.py
nonebot_plugin_qqdetail/matchers.py
nonebot_plugin_qqdetail/utils.py
nonebot_plugin_qqdetail/assets/NotoColorEmoji.ttf
nonebot_plugin_qqdetail/assets/可爱字体.ttf
nonebot_plugin_qqdetail-2.0.0.dist-info/METADATA
nonebot_plugin_qqdetail-2.0.0.dist-info/WHEEL
nonebot_plugin_qqdetail-2.0.0.dist-info/licenses/LICENSE
nonebot_plugin_qqdetail-2.0.0.dist-info/RECORD
