Metadata-Version: 2.4
Name: nonebot-plugin-qqdetail
Version: 2.0.0
Summary: 让机器人查询QQ详细信息 (使用OneBot API)
Project-URL: Repository, https://github.com/006lp/nonebot-plugin-qqdetail
Author-email: 006lp <006lpsuki@gmail.com>
License-File: LICENSE
Keywords: detail,info,nonebot,nonebot2,plugin,qq
Classifier: Development Status :: 4 - Beta
Classifier: Framework :: AsyncIO
Classifier: Intended Audience :: Developers
Classifier: License :: OSI Approved :: GNU Affero General Public License v3
Classifier: Operating System :: OS Independent
Classifier: Programming Language :: Python
Classifier: Programming Language :: Python :: 3
Classifier: Programming Language :: Python :: 3.10
Classifier: Programming Language :: Python :: 3.11
Classifier: Programming Language :: Python :: 3.12
Classifier: Topic :: Communications :: Chat
Classifier: Topic :: Utilities
Requires-Python: <4.0,>=3.10
Requires-Dist: arclet-alconna>=1.8.37
Requires-Dist: emoji>=2.15.0
Requires-Dist: httpx<1.0.0,>=0.27.0
Requires-Dist: nonebot-adapter-onebot<3.0.0,>=2.4.6
Requires-Dist: nonebot-plugin-alconna>=0.57.4
Requires-Dist: nonebot-plugin-localstore>=0.7.4
Requires-Dist: nonebot2[fastapi]<3.0.0,>=2.4.2
Requires-Dist: pillow>=11.3.0
